MANIFEST.in
README.rst
distribute_setup.py
setup.py
tox.ini
musubi/__init__.py
musubi/dnsbl.py
musubi/dnsbllist.py
musubi/ips.py
musubi/main.py
musubi/mx.py
musubi/netdns.py
musubi/scan.py
musubi/spf.py
musubi.egg-info/PKG-INFO
musubi.egg-info/SOURCES.txt
musubi.egg-info/dependency_links.txt
musubi.egg-info/entry_points.txt
musubi.egg-info/namespace_packages.txt
musubi.egg-info/not-zip-safe
musubi.egg-info/requires.txt
musubi.egg-info/top_level.txt
tests/test_netdns.py