Metadata-Version: 1.1
Name: musubi
Version: 0.2
Summary: Musubi is a command-line DNSBL checker and MX toolkit.
Home-page: https://github.com/cakebread/musubi
Author: Rob Cakebread
Author-email: cakebread@gmail.com
License: UNKNOWN
Download-URL: https://github.com/cakebread/musubi/tarball/master
Platform: Any
Classifier: Development Status :: 3 - Alpha
Classifier: License :: OSI Approved :: BSD License
Classifier: Programming Language :: Python
Classifier: Programming Language :: Python :: 2
Classifier: Programming Language :: Python :: 2.7
Classifier: Intended Audience :: Developers
Classifier: Environment :: Console
